dech/__init__.py
dech/test_all.py
dech/version.py
dech-0.0.1.dist-info/LICENSE
dech-0.0.1.dist-info/METADATA
dech-0.0.1.dist-info/WHEEL
dech-0.0.1.dist-info/top_level.txt
dech-0.0.1.dist-info/RECORD
