Metadata-Version: 2.1
Name: dech
Version: 0.0.1
Summary: Declaratively generate simple HTML pages in Python
Home-page: https://github.com/evidlo/dech
Author: Evan Widloski
Author-email: evan_github@widloski.com
License: GPL3
License-File: LICENSE
